README.md
setup.py
MDRefine/MDRefinement.py
MDRefine/__init__.py
MDRefine/_version.py
MDRefine/data_loading.py
MDRefine/hyperminimizer.py
MDRefine/loss_and_minimizer.py
MDRefine.egg-info/PKG-INFO
MDRefine.egg-info/SOURCES.txt
MDRefine.egg-info/dependency_links.txt
MDRefine.egg-info/requires.txt
MDRefine.egg-info/top_level.txt
tests/test_base.py
tests/test_data_loading.py
tests/test_loss_and_minimizer.py
tests/test_mdrefinement.py