Metadata-Version: 2.2
Name: MDRefine
Version: 0.0.10
Summary: A package to perform refinement of MD simulation trajectories.
Home-page: https://github.com/bussilab/MDRefine
Author: Ivan Gilardoni
Classifier: Development Status :: 4 - Beta
Classifier: Intended Audience :: Science/Research
Classifier: License :: OSI Approved :: GNU Lesser General Public License v2 or later (LGPLv2+)
Classifier: Programming Language :: Python :: 3.8
Classifier: Programming Language :: Python :: 3.9
Classifier: Programming Language :: Python :: 3.10
Classifier: Programming Language :: Python :: 3.11
Classifier: Programming Language :: Python :: 3.12
Classifier: Programming Language :: Python :: 3.13
Classifier: Topic :: Scientific/Engineering
Requires-Python: >=3.8
Requires-Dist: numpy
Requires-Dist: pandas
Requires-Dist: jax
Requires-Dist: jaxlib
Requires-Dist: joblib
Dynamic: author
Dynamic: classifier
Dynamic: description
Dynamic: description-content-type
Dynamic: home-page
Dynamic: requires-dist
Dynamic: requires-python
Dynamic: summary
